pandoc_cqu_thesis/Number.py
pandoc_cqu_thesis/__init__.py
pandoc_cqu_thesis/__main__.py
pandoc_cqu_thesis/cleanTitleMeta.py
pandoc_cqu_thesis/codeParsing.py
pandoc_cqu_thesis/equations_no.py
pandoc_cqu_thesis/fieldCode.py
pandoc_cqu_thesis/figures_no.py
pandoc_cqu_thesis/header_convert.py
pandoc_cqu_thesis/horizontal_noindent.py
pandoc_cqu_thesis/meta.py
pandoc_cqu_thesis/parse_md.py
pandoc_cqu_thesis/plainListElem.py
pandoc_cqu_thesis/proof.py
pandoc_cqu_thesis/refs.py
pandoc_cqu_thesis/section_break.py
pandoc_cqu_thesis/sugar_replace.py
pandoc_cqu_thesis/table_no.py
pandoc_cqu_thesis/texcommands.py
pandoc_cqu_thesis/theorem.py
pandoc_cqu_thesis/utils.py
pandoc_cqu_thesis/word_elements.py
pandoc_cqu_thesis-0.15.3.dist-info/entry_points.txt
pandoc_cqu_thesis-0.15.3.dist-info/LICENSE
pandoc_cqu_thesis-0.15.3.dist-info/WHEEL
pandoc_cqu_thesis-0.15.3.dist-info/METADATA
pandoc_cqu_thesis-0.15.3.dist-info/RECORD
