Metadata-Version: 2.1
Name: pandoc-cqu-thesis
Version: 0.15.3
Summary: 用于重庆大学毕业论文的 pandoc filter
Home-page: https://github.com/Hagb/pandoc_cqu_thesis
License: MIT
Keywords: cqu,Chongqing University,pandoc
Author: Hagb Green
Author-email: hagb@hagb.name
Requires-Python: >=3.7,<4.0
Classifier: License :: OSI Approved :: MIT License
Classifier: Programming Language :: Python :: 3
Classifier: Programming Language :: Python :: 3.10
Classifier: Programming Language :: Python :: 3.7
Classifier: Programming Language :: Python :: 3.8
Classifier: Programming Language :: Python :: 3.9
Requires-Dist: panflute (>=2.0)
Requires-Dist: regex (>=2021.4.4,<2022.0.0)
Project-URL: Repository, https://github.com/Hagb/pandoc_cqu_thesis
